ginkgo_ai_client/__init__.py
ginkgo_ai_client/client.py
ginkgo_ai_client/queries.py
ginkgo_ai_client/utils.py
ginkgo_ai_client-0.9.0.dist-info/LICENCE
ginkgo_ai_client-0.9.0.dist-info/METADATA
ginkgo_ai_client-0.9.0.dist-info/WHEEL
ginkgo_ai_client-0.9.0.dist-info/top_level.txt
ginkgo_ai_client-0.9.0.dist-info/RECORD
