Metadata-Version: 2.2
Name: ginkgo_ai_client
Version: 0.9.0
Summary: Client for the public Ginkgo AI API
Author-email: Ginkgo Devs <devs@ginkgobioworks.com>
Requires-Python: >=3.7
License-File: LICENCE
Requires-Dist: biopython
Requires-Dist: pydantic
Requires-Dist: requests
Requires-Dist: tqdm
Requires-Dist: pyyaml
Requires-Dist: pandas
Provides-Extra: test
Requires-Dist: pytest; extra == "test"
Requires-Dist: pytest-xdist; extra == "test"
Provides-Extra: docs
Requires-Dist: sphinx; extra == "docs"
Requires-Dist: sphinx-rtd-theme; extra == "docs"
Requires-Dist: docutils; extra == "docs"
Requires-Dist: myst-parser; extra == "docs"
Requires-Dist: shibuya; extra == "docs"
